assertme/__init__.py
assertme/annotations.py
assertme/base.py
assertme/datetime.py
assertme/instance.py
assertme/py.typed
assertme/pydantic.py
assertme/uuid.py
assertme-0.1.0.dist-info/LICENSE
assertme-0.1.0.dist-info/METADATA
assertme-0.1.0.dist-info/WHEEL
assertme-0.1.0.dist-info/RECORD
