Metadata-Version: 2.3
Name: assertme
Version: 0.1.0
Summary: Utilities for asserting without caring (much)
License: MIT
Author: Gerard Solé
Author-email: g.sole.ca@gmail.com
Requires-Python: >=3.11
Classifier: License :: OSI Approved :: MIT License
Classifier: Programming Language :: Python :: 3
Classifier: Programming Language :: Python :: 3.11
Classifier: Programming Language :: Python :: 3.12
Classifier: Programming Language :: Python :: 3.13
Requires-Dist: pydantic (>=2.5.0,<3.0.0)
Requires-Dist: python-dateutil (>=2.9.0.post0,<3.0.0)
Requires-Dist: types-python-dateutil (>=2.9.0.20241206,<3.0.0.0)
Project-URL: Issues, https://github.com/GerardSoleCa/assertme/issues
Project-URL: Repository, https://github.com/GerardSoleCa/assertme.git
